ond_visualization/__init__.py
ond_visualization-1.0.2.dist-info/METADATA
ond_visualization-1.0.2.dist-info/WHEEL
ond_visualization-1.0.2.dist-info/licenses/LICENSE
ond_visualization-1.0.2.dist-info/RECORD
