Metadata-Version: 2.4
Name: ond_visualization
Version: 1.0.2
Summary: A simple tool to visualize the IBL Dataset using the ONE API
Project-URL: Homepage, https://github.com/GerritFischer/ond_visualization
Author-email: "Fischer, Tran, Wojak" <gerrit.fischer2@icloud.com>
License-File: LICENSE
Classifier: License :: OSI Approved :: MIT License
Classifier: Operating System :: OS Independent
Classifier: Programming Language :: Python :: 3
Requires-Python: >=3.8
Requires-Dist: brainrender==2.1.9
Requires-Dist: ibllib==2.34.0
Requires-Dist: matplotlib==3.8.4
Requires-Dist: numpy==1.26.4
Requires-Dist: one-api==2.11.2
Requires-Dist: vedo==2024.5.1
